cases/__init__.py
pycases-0.1.4.dist-info/licenses/LICENSE
pycases-0.1.4.dist-info/METADATA
pycases-0.1.4.dist-info/WHEEL
pycases-0.1.4.dist-info/top_level.txt
pycases-0.1.4.dist-info/RECORD
