Metadata-Version: 2.4
Name: pycases
Version: 0.1.4
Summary: A case conversion library with Unicode support
Author-email: Ross MacArthur <ross@macarthur.io>
License: MIT
Project-URL: Homepage, https://github.com/rossmacarthur/pycases
Project-URL: Repository, https://github.com/rossmacarthur/pycases
Keywords: convert,case,snake,camel,pascal
Classifier: Development Status :: 3 - Alpha
Classifier: Intended Audience :: Developers
Classifier: License :: OSI Approved :: MIT License
Classifier: Natural Language :: English
Classifier: Operating System :: OS Independent
Classifier: Programming Language :: Rust
Classifier: Programming Language :: Python
Classifier: Programming Language :: Python :: 3.7
Classifier: Programming Language :: Python :: 3.8
Classifier: Programming Language :: Python :: 3.9
Classifier: Programming Language :: Python :: 3.10
Classifier: Programming Language :: Python :: 3.11
Classifier: Programming Language :: Python :: 3.12
Classifier: Programming Language :: Python :: 3.13
Requires-Python: >=3.7
License-File: LICENSE
Requires-Dist: py-anycase
Dynamic: license-file
